LMIPy/__init__.py
LMIPy/collection.py
LMIPy/dataAPI.py
LMIPy/dataset.py
LMIPy/geometry.py
LMIPy/image.py
LMIPy/imageCollection.py
LMIPy/layer.py
LMIPy/lmipy.py
LMIPy/metadata.py
LMIPy/table.py
LMIPy/utils.py
LMIPy/vocabulary.py
LMIPy/widget.py
LMIPy-0.6.2.dist-info/LICENSE
LMIPy-0.6.2.dist-info/METADATA
LMIPy-0.6.2.dist-info/WHEEL
LMIPy-0.6.2.dist-info/top_level.txt
LMIPy-0.6.2.dist-info/RECORD
