Metadata-Version: 2.1
Name: LMIPy
Version: 0.6.2
Summary: Pythonic interface to various backend ecosystems related geospatial data.
Home-page: https://github.com/Vizzuality/LMIPy
Author: Vizzuality
Author-email: benjamin.laken@vizzuality.com
License: MIT
Platform: UNKNOWN
Classifier: Programming Language :: Python :: 3
Classifier: Programming Language :: Python :: 3.7
Classifier: License :: OSI Approved :: MIT License
Classifier: Operating System :: OS Independent
Requires-Dist: requests (>=2.2.0)
Requires-Dist: pypng (>=0.0.19)
Requires-Dist: folium (==0.8.3)
Requires-Dist: geopandas (>=0.4.1)
Requires-Dist: geojson (>=2.4.0)
Requires-Dist: tqdm (>=4.21.0)
